check4updates/__init__.py
check4updates-0.0.2.dist-info/LICENSE
check4updates-0.0.2.dist-info/METADATA
check4updates-0.0.2.dist-info/WHEEL
check4updates-0.0.2.dist-info/top_level.txt
check4updates-0.0.2.dist-info/RECORD
