Metadata-Version: 2.1
Name: check4updates
Version: 0.0.2
Summary: A library for Python developers that prompts your users to upgrade when a new version of your package is released
Home-page: https://check4updates.readthedocs.io/en/latest/
Author: Matthew Reid
Author-email: alpha.reliability@gmail.com
License: MIT
Project-URL: Documentation, https://check4updates.readthedocs.io/en/latest/
Project-URL: Source Code, https://github.com/MatthewReid854/check4updates
Keywords: check,auto,automatic,upgrade,update,updates,updater,upgrader,package,utility,new,release,autoupgrade,autoupdate,prompt,users,developers,interactive,pip
Platform: UNKNOWN
Classifier: Intended Audience :: Developers
Classifier: Topic :: Software Development :: Libraries :: Python Modules
Classifier: Programming Language :: Python :: 3
Classifier: Development Status :: 4 - Beta
Classifier: License :: OSI Approved :: MIT License
Requires-Dist: requests (>=2.24.0)
